bulc.py
bulc-0.1.6.dist-info/LICENSE
bulc-0.1.6.dist-info/METADATA
bulc-0.1.6.dist-info/WHEEL
bulc-0.1.6.dist-info/entry_points.txt
bulc-0.1.6.dist-info/top_level.txt
bulc-0.1.6.dist-info/RECORD
