Metadata-Version: 2.1
Name: bulc
Version: 0.1.6
Summary: Build file generator for GNU Make.
Author-email: Alex Amellal <bulgogi@alexamellal.com>
Project-URL: Homepage, https://bulgogi.dev
Project-URL: Issues, https://github.com/high-intensity-prototyping-labs/bulc/issues
Classifier: Development Status :: 2 - Pre-Alpha
Classifier: Programming Language :: C
Classifier: Programming Language :: Python
Classifier: Intended Audience :: Developers
Classifier: Operating System :: MacOS
Classifier: Topic :: Software Development :: Build Tools
Requires-Python: >=3.8
License-File: LICENSE
Requires-Dist: bulgogi ==0.1.5
Requires-Dist: jinja2 ==3.1.3
